[
  {
    "explain": "n. Politeness.", 
    "word": "complaisance"
  }, 
  {
    "explain": "n. General structure, form, or outline.", 
    "word": "conformation"
  }, 
  {
    "explain": "adj. Exciting or exhilarating to the mind.", 
    "word": "racy"
  }, 
  {
    "explain": "n. Proclamation.", 
    "word": "annunciation"
  }, 
  {
    "explain": "adj. That can not be heard.", 
    "word": "inaudible"
  }, 
  {
    "explain": "n. A union of two characters representing a single sound.", 
    "word": "digraph"
  }, 
  {
    "explain": "adj. Sensual.", 
    "word": "carnal"
  }, 
  {
    "explain": "v. To form an idea, mental image or thought of.", 
    "word": "conceive"
  }, 
  {
    "explain": "n. One who or that which aids or helps, especially when regarded as subsidiary or accessory.", 
    "word": "auxiliary"
  }, 
  {
    "explain": "adj. Worthy of scorn or disdain.", 
    "word": "contemptible"
  }, 
  {
    "explain": "adj. Capable of being disjoined or divided.", 
    "word": "separable"
  }, 
  {
    "explain": "n. Patient courage.", 
    "word": "fortitude"
  }, 
  {
    "explain": "adj. Conformed to a just claim according to established laws or usage.", 
    "word": "rightful"
  }, 
  {
    "explain": "n. One who lives by robbery and plunder.", 
    "word": "brigand"
  }, 
  {
    "explain": "n. The time that life continues.", 
    "word": "lifetime"
  }, 
  {
    "explain": "adj. Comprehensible.", 
    "word": "intelligible"
  }, 
  {
    "explain": "v. To present a verbal or written protest to those who have power to right or prevent a wrong.", 
    "word": "remonstrate"
  }, 
  {
    "explain": "v. To swing back and forth.", 
    "word": "oscillate"
  }, 
  {
    "explain": "v. To make more sharp, severe, or virulent.", 
    "word": "exacerbate"
  }, 
  {
    "explain": "v. To predict or foretell, especially under divine inspiration and guidance.", 
    "word": "prophesy"
  }
]