[
  {
    "explain": "adj. Not having an adequate or proper supply or amount.", 
    "word": "deficient"
  }, 
  {
    "explain": "adj. Constituting or consisting of salt.", 
    "word": "saline"
  }, 
  {
    "explain": "n. The body of men constituting the official advisors of the executive head of a nation.", 
    "word": "cabinet"
  }, 
  {
    "explain": "adj. Slovenly in appearance.", 
    "word": "frowzy"
  }, 
  {
    "explain": "n. The branch of physics that treats the phenomena caused by the action of forces.", 
    "word": "mechanics"
  }, 
  {
    "explain": "v. To separate.", 
    "word": "unyoke"
  }, 
  {
    "explain": "adj. Feasible.", 
    "word": "practicable"
  }, 
  {
    "explain": "n. A lack of variety.", 
    "word": "monotony"
  }, 
  {
    "explain": "v. To happen again or repeatedly, especially at regular intervals.", 
    "word": "recur"
  }, 
  {
    "explain": "adj. Pertaining to, contained in, or warranted by the Holy Scriptures.", 
    "word": "Scriptural"
  }, 
  {
    "explain": "v. To continue steadfast against opposition.", 
    "word": "persist"
  }, 
  {
    "explain": "adj. Made to resemble something else.", 
    "word": "counterfeit"
  }, 
  {
    "explain": "n. The state or period of being a student.", 
    "word": "pupilage"
  }, 
  {
    "explain": "n. The voluntary consecration or relinquishment of something to an end or cause.", 
    "word": "dedication"
  }, 
  {
    "explain": "n. Fewness.", 
    "word": "paucity"
  }, 
  {
    "explain": "n. That which is indispensably requisite to an end desired.", 
    "word": "necessity"
  }, 
  {
    "explain": "n. A young swan.", 
    "word": "cygnet"
  }, 
  {
    "explain": "n. A person engaged in manufacturing as a business.", 
    "word": "manufacturer"
  }, 
  {
    "explain": "adj. Irrevocable.", 
    "word": "irreversible"
  }, 
  {
    "explain": "v. To endow with a privilege, especially with the right to vote.", 
    "word": "enfranchise"
  }
]