[
  {
    "explain": "n. A fictitious narrative presented as historical, but without any basis of fact.", 
    "word": "myth"
  }, 
  {
    "explain": "n. Any growth of leaves.", 
    "word": "foliage"
  }, 
  {
    "explain": "n. A mental condition of fixed opposition to or dislike of some particular thing.", 
    "word": "aversion"
  }, 
  {
    "explain": "adj. Not copied nor produced by imitation.", 
    "word": "original"
  }, 
  {
    "explain": "adj. Pertaining to or consisting of air or gas.", 
    "word": "pneumatic"
  }, 
  {
    "explain": "adj. Having the spirit or sentiment of rural life.", 
    "word": "pastoral"
  }, 
  {
    "explain": "adj. Watery.", 
    "word": "hydrous"
  }, 
  {
    "explain": "adj. Tending to reconcile.", 
    "word": "conciliatory"
  }, 
  {
    "explain": "v. To spend sparingly.", 
    "word": "economize"
  }, 
  {
    "explain": "v. To remove and plant in another place.", 
    "word": "transplant"
  }, 
  {
    "explain": "n. A scholar who makes needless and inopportune display of his learning.", 
    "word": "pedant"
  }, 
  {
    "explain": "v. To place in a detached state or situation.", 
    "word": "insulate"
  }, 
  {
    "explain": "v. To assign or affix a date to earlier than the actual one.", 
    "word": "antedate"
  }, 
  {
    "explain": "adv. In a vague or uncertain way.", 
    "word": "indefinitely"
  }, 
  {
    "explain": "adj. Taking unlawful or exorbitant interest on money loaned.", 
    "word": "usurious"
  }, 
  {
    "explain": "adj. Pertaining to education or schools.", 
    "word": "scholastic"
  }, 
  {
    "explain": "n. A coming to stopping-place or destination.", 
    "word": "arrival"
  }, 
  {
    "explain": "adj. Very hateful.", 
    "word": "abominable"
  }, 
  {
    "explain": "v. To confine within bounds.", 
    "word": "circumscribe"
  }, 
  {
    "explain": "adj. Evil.", 
    "word": "sinister"
  }
]