[
  {
    "explain": "['t\u0259:m\u0254il]", 
    "word": "turmoil"
  }, 
  {
    "explain": "[`sist\u0259'm\u00e6tik]", 
    "word": "systematic"
  }, 
  {
    "explain": "['j\u0254g\u0259t]", 
    "word": "yogurt"
  }, 
  {
    "explain": "[\u0259'beit]", 
    "word": "abate"
  }, 
  {
    "explain": "['ni\u0259li]", 
    "word": "nearly"
  }, 
  {
    "explain": "[l\u0259un]", 
    "word": "loan"
  }, 
  {
    "explain": "[ri:'it\u0259reit]", 
    "word": "reiterate"
  }, 
  {
    "explain": "[ri'vaivl]", 
    "word": "revival"
  }, 
  {
    "explain": "[ri'fre\u0283]", 
    "word": "refresh"
  }, 
  {
    "explain": "[\u0259'd\u0254pt]", 
    "word": "adopt"
  }, 
  {
    "explain": "[raip]", 
    "word": "ripe"
  }, 
  {
    "explain": "[in'trepid]", 
    "word": "intrepid"
  }, 
  {
    "explain": "[ri'ta:d]", 
    "word": "retard"
  }, 
  {
    "explain": "['\u00e6v\u0259nju:]", 
    "word": "avenue"
  }, 
  {
    "explain": "[kri'ti:k]", 
    "word": "critique"
  }, 
  {
    "explain": "[di'd\u0292ektid]", 
    "word": "dejected"
  }, 
  {
    "explain": "['t\u0259:tl]", 
    "word": "turtle"
  }, 
  {
    "explain": "['l\u0254:d\u0259bl]", 
    "word": "laudable"
  }, 
  {
    "explain": "[m\u0259u'zeiik]", 
    "word": "mosaic"
  }, 
  {
    "explain": "['d\u0292u:\u0259lri]", 
    "word": "jewelry"
  }
]