[
  {
    "explain": "['n\u0259utis\u0259bl]", 
    "word": "noticeable"
  }, 
  {
    "explain": "['midieit]", 
    "word": "mediate"
  }, 
  {
    "explain": "[in'laitnm\u0259nt]", 
    "word": "enlightenment"
  }, 
  {
    "explain": "['impr\u0259'prai\u0259ti]", 
    "word": "impropriety"
  }, 
  {
    "explain": "['\u00e6dv\u0259taiz]", 
    "word": "advertise"
  }, 
  {
    "explain": "[pr\u0259'fes]", 
    "word": "profess"
  }, 
  {
    "explain": "[pr\u0259'fju:s]", 
    "word": "profuse"
  }, 
  {
    "explain": "['spi:di]", 
    "word": "speedy"
  }, 
  {
    "explain": "[\u0254:'di:l]", 
    "word": "ordeal"
  }, 
  {
    "explain": "[`aut'g\u00e6s]", 
    "word": "outgas"
  }, 
  {
    "explain": "['pru:fri:d]", 
    "word": "proofread"
  }, 
  {
    "explain": "[in'kwizitiv]", 
    "word": "inquisitive"
  }, 
  {
    "explain": "[\u0259's\u028cmp\u0283\u0259n]", 
    "word": "assumption"
  }, 
  {
    "explain": "[pri'sais]", 
    "word": "precise"
  }, 
  {
    "explain": "[di'm\u0254li\u0283]", 
    "word": "demolish"
  }, 
  {
    "explain": "[k\u028clt]", 
    "word": "cult"
  }, 
  {
    "explain": "['sikn]", 
    "word": "sicken"
  }, 
  {
    "explain": "[\u0259'pi:l]", 
    "word": "appeal"
  }, 
  {
    "explain": "[`\u028cnd\u0259'laii\u014b]", 
    "word": "underlying"
  }, 
  {
    "explain": "['nikl]", 
    "word": "nickel"
  }
]