[
  {
    "explain": "[in'v\u0259uk]", 
    "word": "invoke"
  }, 
  {
    "explain": "['eks\u0259d\u0259s]", 
    "word": "exodus"
  }, 
  {
    "explain": "[di'm\u0251:ndi\u014b]", 
    "word": "demanding"
  }, 
  {
    "explain": "[daiv]", 
    "word": "dive"
  }, 
  {
    "explain": "[in'\u0261r\u0259ust]", 
    "word": "engrossed"
  }, 
  {
    "explain": "['\u028cnd\u0259'teiki\u014b]", 
    "word": "undertaking"
  }, 
  {
    "explain": "['gr\u00e6nit]", 
    "word": "granite"
  }, 
  {
    "explain": "['b\u00e6t\u0259]", 
    "word": "batter"
  }, 
  {
    "explain": "['p\u00e6r\u0259laiz]", 
    "word": "paralyze"
  }, 
  {
    "explain": "['h\u0254minid]", 
    "word": "hominid"
  }, 
  {
    "explain": "[\u0259'n\u00e6l\u0259sis]", 
    "word": "analysis"
  }, 
  {
    "explain": "['listlis]", 
    "word": "listless"
  }, 
  {
    "explain": "[\u0254:di't\u0254:ri\u0259m]", 
    "word": "auditorium"
  }, 
  {
    "explain": "[\u0259'd\u00e6pt\u0259bl]", 
    "word": "adaptable"
  }, 
  {
    "explain": "[sik]", 
    "word": "sick"
  }, 
  {
    "explain": "[`hens'f\u0254:\u03b8]", 
    "word": "henceforth"
  }, 
  {
    "explain": "[ri'pjudieit]", 
    "word": "repudiate"
  }, 
  {
    "explain": "['d\u0292el\u0259s]", 
    "word": "jealous"
  }, 
  {
    "explain": "[k\u0259n'f\u0259:m]", 
    "word": "confirm"
  }, 
  {
    "explain": "[\u0259'li:vieit]", 
    "word": "alleviate"
  }
]