[
  {
    "explain": "[reid]", 
    "word": "raid"
  }, 
  {
    "explain": "['si:kw\u0259ns]", 
    "word": "sequence"
  }, 
  {
    "explain": "['s\u0259udi\u0259m]", 
    "word": "sodium"
  }, 
  {
    "explain": "[ri'zent]", 
    "word": "resent"
  }, 
  {
    "explain": "[h\u028cm]", 
    "word": "hum"
  }, 
  {
    "explain": "['timb\u0259]", 
    "word": "timber"
  }, 
  {
    "explain": "[b\u0254nd]", 
    "word": "bond"
  }, 
  {
    "explain": "[ni'glekt]", 
    "word": "neglect"
  }, 
  {
    "explain": "['kw\u0254ntifai]", 
    "word": "quantify"
  }, 
  {
    "explain": "[mi'\u00e6nd\u0259]", 
    "word": "meander"
  }, 
  {
    "explain": "['k\u00e6t\u0259pil\u0259]", 
    "word": "caterpillar"
  }, 
  {
    "explain": "[`\u0251:ti'z\u00e6n]", 
    "word": "artisan"
  }, 
  {
    "explain": "[li:s]", 
    "word": "lease"
  }, 
  {
    "explain": "['disiplin]", 
    "word": "discipline"
  }, 
  {
    "explain": "[k\u0259n'sist\u0259ntli]", 
    "word": "consistently"
  }, 
  {
    "explain": "['v\u0259:dikt]", 
    "word": "verdict"
  }, 
  {
    "explain": "[bi'nev\u0259l\u0259nt]", 
    "word": "benevolent"
  }, 
  {
    "explain": "[pl\u028cnd\u0292]", 
    "word": "plunge"
  }, 
  {
    "explain": "['n\u0254lid\u0292\u0259bl]", 
    "word": "knowledgeable"
  }, 
  {
    "explain": "['s\u00e6tis'f\u00e6kt\u0259ri]", 
    "word": "satisfactory"
  }
]